[
  {
    "id": 1,
    "title": "Basics",
    "sections": [
      {
        "id": 1,
        "title": "Basics - The Big Picture",
        "description": "You really want to make sure you have these basics covered before tackling other checklists.",
        "items": [
          { "id": "m1s1_1",
            "title": "Open a checking account",
            "description": "Description"
          },
          { "id": "m1s1_2",
            "title": "Title",
            "description": "Description"
          },
          { "id": "m1s1_3",
            "title": "Title",
            "description": "Description"
          },
          { "id": "m1s1_4",
            "title": "Title",
            "description": "Description"
          },
          { "id": "m1s1_5",
            "title": "Title",
            "description": "Description"
          },
          { "id": "m1s1_6",
            "title": "Title",
            "description": "Description"
          }
        ]
      },
      {
        "id": 2,
        "title": "Section Title "
      },
      {
        "id": 3,
        "title": "Section Title "
      },
      {
        "id": 4,
        "title": "Section Title "
      },
      {
        "id": 5,
        "title": "Section Title "
      }
    ]
  },

  { "id": 2,
    "title": "Module Title",
    "sections": [
      {
        "id": 1,
        "description": "",
        "title": "Section Title "
      },
      {
        "id": 2,
        "title": "Section Title "
      },
      {
        "id": 3,
        "title": "Section Title "
      },
      {
        "id": 4,
        "title": "Section Title "
      },
      {
        "id": 5,
        "title": "Section Title "
      }
    ]
  },

  { "id": 3,
    "title": "Module Title",
    "sections": [
      {
        "id": 1,
        "title": "Section Title "
      },
      {
        "id": 2,
        "title": "Section Title "
      },
      {
        "id": 3,
        "title": "Section Title "
      },
      {
        "id": 4,
        "title": "Section Title "
      },
      {
        "id": 5,
        "title": "Section Title "
      }
    ]
  },

  { "id": 4,
    "title": "Module Title",
    "sections": [
      {
        "id": 1,
        "title": "Section Title "
      },
      {
        "id": 2,
        "title": "Section Title "
      },
      {
        "id": 3,
        "title": "Section Title "
      },
      {
        "id": 4,
        "title": "Section Title "
      },
      {
        "id": 5,
        "title": "Section Title "
      }
    ]
  }

]